<KicadtoNgspice><source><v3 name="Source type">2sinwt</v3><v1 name="Source type">5v</v1><v2 name="Source type">5v</v2><v1 name="Source type">s1</v1><v2 name="Source type">s2</v2><v1 name="Source type">dc<field1 name="Value">5</field1></v1><v2 name="Source type">dc<field1 name="Value">5</field1></v2></source><model><u3 name="type">adc_bridge<field1 name="Enter value for in_low (default=1.0)" /><field2 name="Enter value for in_high (default=2.0)" /><field3 name="Enter Rise Delay (default=1.0e-9)" /><field4 name="Enter Fall Delay (default=1.0e-9)" /></u3><u2 name="type">aishwarya_frequencydivider<field5 name="Enter Rise Delay (default=1.0e-9)" /><field6 name="Enter Fall Delay (default=1.0e-9)" /><field7 name="Enter Input Load (default=1.0e-12)" /><field8 name="Enter Instance ID (Between 0-99)" /></u2><u4 name="type">dac_bridge<field9 name="Enter value for out_low (default=0.0)" /><field10 name="Enter value for out_high (default=5.0)" /><field11 name="Enter value for out_undef (default=0.5)" /><field12 name="Enter value for input load (default=1.0e-12)" /><field13 name="Enter the Rise Time (default=1.0e-9)" /><field14 name="Enter the Fall Time (default=1.0e-9)" /></u4><u2 name="type">adc_bridge<field1 name="Enter value for in_low (default=1.0)" /><field2 name="Enter value for in_high (default=2.0)" /><field3 name="Enter Rise Delay (default=1.0e-9)" /><field4 name="Enter Fall Delay (default=1.0e-9)" /></u2></model><devicemodel /><subcircuit><x1><field>C:\FOSSEE\eSim\library\SubcircuitLibrary\lm_741</field></x1></subcircuit><analysis><ac><field1 name="Lin">true</field1><field2 name="Dec">false</field2><field3 name="Oct">false</field3><field4 name="Start Frequency" /><field5 name="Stop Frequency" /><field6 name="No. of points" /><field7 name="Start Fre Combo">Hz</field7><field8 name="Stop Fre Combo">Hz</field8></ac><dc><field1 name="Source 1">v1</field1><field2 name="Start">0</field2><field3 name="Increment">1</field3><field4 name="Stop">20</field4><field5 name="Operating Point">0</field5><field6 name="Start Combo">mV or mA</field6><field7 name="Increment Combo">mV or mA</field7><field8 name="Stop Combo">mV or mA</field8><field9 name="Source 2">v2</field9><field10 name="Start">0</field10><field11 name="Increment">1</field11><field12 name="Stop">20</field12><field13 name="Start Combo">mV or mA</field13><field14 name="Increment Combo">mV or mA</field14><field15 name="Stop Combo">mV or mA</field15></dc><tran><field1 name="Start Time">0</field1><field2 name="Step Time">10</field2><field3 name="Stop Time">1000</field3><field4 name="Start Combo">ms</field4><field5 name="Step Combo">ms</field5><field6 name="Stop Combo">ms</field6></tran></analysis></KicadtoNgspice>